medallion_etl/__init__.py
medallion_etl/bronze/__init__.py
medallion_etl/bronze/extractors.py
medallion_etl/cli/__init__.py
medallion_etl/cli/commands.py
medallion_etl/config/__init__.py
medallion_etl/config/settings.py
medallion_etl/connectors/__init__.py
medallion_etl/connectors/base.py
medallion_etl/connectors/sql.py
medallion_etl/core/__init__.py
medallion_etl/core/pipeline.py
medallion_etl/core/task.py
medallion_etl/gold/__init__.py
medallion_etl/gold/transformers.py
medallion_etl/schemas/__init__.py
medallion_etl/schemas/base.py
medallion_etl/silver/__init__.py
medallion_etl/silver/validators.py
medallion_etl/templates/__init__.py
medallion_etl/templates/pipeline_template.py
medallion_etl/utils/__init__.py
medallion_etl/utils/helpers.py
medallion_etl/utils/logging_utils.py
medallion_etl-0.1.29.dist-info/licenses/LICENSE
medallion_etl-0.1.29.dist-info/METADATA
medallion_etl-0.1.29.dist-info/WHEEL
medallion_etl-0.1.29.dist-info/entry_points.txt
medallion_etl-0.1.29.dist-info/top_level.txt
medallion_etl-0.1.29.dist-info/RECORD
