Metadata-Version: 2.4
Name: medallion-etl
Version: 0.1.29
Summary: Una librería modular para construir data pipelines con arquitectura medallion
Home-page: https://github.com/JuanManiglia/medallion-etl
Author: Data Engineering Team
Author-email: Juan Maniglia <jamr1989@gmail.com>
License: MIT
Project-URL: Homepage, https://github.com/JuanManiglia/medallion-etl
Classifier: Programming Language :: Python :: 3
Classifier: Programming Language :: Python :: 3.11
Classifier: License :: OSI Approved :: MIT License
Classifier: Operating System :: OS Independent
Classifier: Topic :: Software Development :: Libraries
Classifier: Topic :: Database
Requires-Python: >=3.11
License-File: LICENSE
Requires-Dist: polars>=1.30
Requires-Dist: pydantic>=2.7
Requires-Dist: sqlalchemy>=2.0
Requires-Dist: prefect>=3.0
Requires-Dist: requests>=2.25.0
Requires-Dist: rich>=14.0.0
Requires-Dist: typer>=0.9.0
Provides-Extra: dev
Requires-Dist: pytest>=7.0.0; extra == "dev"
Requires-Dist: black>=23.0.0; extra == "dev"
Requires-Dist: isort>=5.10.0; extra == "dev"
Requires-Dist: mypy>=1.0.0; extra == "dev"
Dynamic: author
Dynamic: home-page
Dynamic: license-file
Dynamic: requires-python
